LICENSE.txt
MANIFEST.in
README.rst
setup.py
cmsplugin_bootstrap_carousel/__init__.py
cmsplugin_bootstrap_carousel/cms_plugins.py
cmsplugin_bootstrap_carousel/models.py
cmsplugin_bootstrap_carousel/models_default.py
cmsplugin_bootstrap_carousel/models_filer.py
cmsplugin_bootstrap_carousel.egg-info/PKG-INFO
cmsplugin_bootstrap_carousel.egg-info/SOURCES.txt
cmsplugin_bootstrap_carousel.egg-info/dependency_links.txt
cmsplugin_bootstrap_carousel.egg-info/not-zip-safe
cmsplugin_bootstrap_carousel.egg-info/pbr.json
cmsplugin_bootstrap_carousel.egg-info/requires.txt
cmsplugin_bootstrap_carousel.egg-info/top_level.txt
cmsplugin_bootstrap_carousel/migrations/0001_initial.py
cmsplugin_bootstrap_carousel/migrations/0002_auto__add_field_carousel_show_controls__add_field_carousel_show_indica.py
cmsplugin_bootstrap_carousel/migrations/__init__.py
cmsplugin_bootstrap_carousel/templates/cmsplugin_bootstrap_carousel/carousel.html
requirements/common.txt
requirements/development.txt
requirements/production.txt
requirements/testing.txt
tests/__init__.py
tests/settings.py