Metadata-Version: 1.1
Name: cmsplugin-bootstrap-carousel
Version: 0.2.2
Summary: Bootstrap carousel plugin for django-cms
Home-page: https://github.com/nimbis/cmsplugin-bootstrap-carousel/
Author: Nimbis Services, Inc.
Author-email: devops@nimbisservices.com
License: BSD
Keywords: django,django-cms,bootstrap,carousel
Platform: UNKNOWN
Classifier: Programming Language :: Python
Classifier: Environment :: Web Environment
Classifier: Development Status :: 4 - Beta
Classifier: Intended Audience :: Developers
Classifier: License :: OSI Approved :: BSD License
Classifier: Operating System :: OS Independent
Classifier: Framework :: Django
